noodler/__init__.py
noodler/tracing/__init__.py
noodler/tracing/config.py
noodler/tracing/constants.py
noodler/tracing/openai.py
noodler/tracing/types.py
noodler/tracing/utils.py
noodler_sdk-0.1.0.dist-info/METADATA
noodler_sdk-0.1.0.dist-info/WHEEL
noodler_sdk-0.1.0.dist-info/licenses/LICENSE
noodler_sdk-0.1.0.dist-info/RECORD
