Metadata-Version: 2.4
Name: noodler-sdk
Version: 0.1.0
Summary: Python library for the Noodler API
Author: Noodler
License: MIT
License-File: LICENSE
Keywords: noodler,observability,openai,opentelemetry,tracing
Classifier: Development Status :: 4 - Beta
Classifier: Intended Audience :: Developers
Classifier: License :: OSI Approved :: MIT License
Classifier: Programming Language :: Python :: 3
Classifier: Programming Language :: Python :: 3.10
Classifier: Programming Language :: Python :: 3.11
Classifier: Programming Language :: Python :: 3.12
Requires-Python: >=3.10
Requires-Dist: openai>=2.14.0
Requires-Dist: opentelemetry-api>=1.39.1
Requires-Dist: opentelemetry-exporter-otlp-proto-http>=1.39.1
Requires-Dist: opentelemetry-sdk>=1.39.1
